{"dia":"2022-07-24T00:00:00","manana":{"hora":1,"numeros":["5","4","4"],"sorteo_Id":-1,"numeroSorteo":1960,"fecha":"2022-07-24T12:55:00","estado":3,"vigencia":"2022-09-22T00:00:00","tipoSorteoCode":"Tres_Monazos","tipoSorteoName":"Tres_Monazos"},"mediaTarde":{"hora":2,"numeros":["4","5","9"],"sorteo_Id":-1,"numeroSorteo":1961,"fecha":"2022-07-24T16:30:00","estado":3,"vigencia":"2022-09-22T00:00:00","tipoSorteoCode":"Tres_Monazos","tipoSorteoName":"Tres_Monazos"},"tarde":{"hora":3,"numeros":["1","2","7"],"sorteo_Id":-1,"numeroSorteo":1962,"fecha":"2022-07-24T19:30:00","estado":3,"vigencia":"2022-09-22T00:00:00","tipoSorteoCode":"Tres_Monazos","tipoSorteoName":"Tres_Monazos"}}