{"dia":"2022-12-18T00:00:00","manana":{"hora":1,"numeros":["3","4","1"],"sorteo_Id":-1,"numeroSorteo":2401,"fecha":"2022-12-18T12:55:00","estado":3,"vigencia":"2023-02-16T00:00:00","tipoSorteoCode":"Tres_Monazos","tipoSorteoName":"Tres_Monazos"},"mediaTarde":{"hora":2,"numeros":["0","4","7"],"sorteo_Id":-1,"numeroSorteo":2402,"fecha":"2022-12-18T16:30:00","estado":3,"vigencia":"2023-02-16T00:00:00","tipoSorteoCode":"Tres_Monazos","tipoSorteoName":"Tres_Monazos"},"tarde":{"hora":3,"numeros":["1","5","9"],"sorteo_Id":-1,"numeroSorteo":2403,"fecha":"2022-12-18T19:30:00","estado":3,"vigencia":"2023-02-16T00:00:00","tipoSorteoCode":"Tres_Monazos","tipoSorteoName":"Tres_Monazos"}}