{"dia":"2023-01-28T00:00:00","manana":{"hora":1,"numeros":["4","8","4"],"sorteo_Id":-1,"numeroSorteo":2516,"fecha":"2023-01-28T12:55:00","estado":3,"vigencia":"2023-03-30T00:00:00","tipoSorteoCode":"Tres_Monazos","tipoSorteoName":"Tres_Monazos"},"mediaTarde":{"hora":2,"numeros":["3","5","5"],"sorteo_Id":-1,"numeroSorteo":2517,"fecha":"2023-01-28T16:30:00","estado":3,"vigencia":"2023-03-30T00:00:00","tipoSorteoCode":"Tres_Monazos","tipoSorteoName":"Tres_Monazos"},"tarde":{"hora":3,"numeros":["5","1","9"],"sorteo_Id":-1,"numeroSorteo":2518,"fecha":"2023-01-28T19:30:00","estado":3,"vigencia":"2023-03-30T00:00:00","tipoSorteoCode":"Tres_Monazos","tipoSorteoName":"Tres_Monazos"}}