{"dia":"2023-08-03T00:00:00","manana":{"hora":1,"numeros":["0","8","3"],"sorteo_Id":-1,"numeroSorteo":3065,"fecha":"2023-08-03T12:55:00","estado":3,"vigencia":"2023-10-05T00:00:00","tipoSorteoCode":"Tres_Monazos","tipoSorteoName":"Tres_Monazos"},"mediaTarde":{"hora":2,"numeros":["4","0","1"],"sorteo_Id":-1,"numeroSorteo":3066,"fecha":"2023-08-03T16:30:00","estado":3,"vigencia":"2023-10-05T00:00:00","tipoSorteoCode":"Tres_Monazos","tipoSorteoName":"Tres_Monazos"},"tarde":{"hora":3,"numeros":["5","7","6"],"sorteo_Id":-1,"numeroSorteo":3067,"fecha":"2023-08-03T19:30:00","estado":3,"vigencia":"2023-10-05T00:00:00","tipoSorteoCode":"Tres_Monazos","tipoSorteoName":"Tres_Monazos"}}