{"dia":"2024-02-01T00:00:00","manana":{"hora":1,"numeros":["3","7","9"],"sorteo_Id":-1,"numeroSorteo":3603,"fecha":"2024-02-01T12:55:00","estado":3,"vigencia":"2024-04-04T00:00:00","tipoSorteoCode":"Tres_Monazos","tipoSorteoName":"Tres_Monazos"},"mediaTarde":{"hora":2,"numeros":["4","7","3"],"sorteo_Id":-1,"numeroSorteo":3604,"fecha":"2024-02-01T16:30:00","estado":3,"vigencia":"2024-04-04T00:00:00","tipoSorteoCode":"Tres_Monazos","tipoSorteoName":"Tres_Monazos"},"tarde":{"hora":3,"numeros":["7","9","2"],"sorteo_Id":-1,"numeroSorteo":3605,"fecha":"2024-02-01T19:30:00","estado":3,"vigencia":"2024-04-04T00:00:00","tipoSorteoCode":"Tres_Monazos","tipoSorteoName":"Tres_Monazos"}}