{"dia":"2024-02-16T00:00:00","manana":{"hora":1,"numeros":["8","9","0"],"sorteo_Id":-1,"numeroSorteo":3648,"fecha":"2024-02-16T12:55:00","estado":3,"vigencia":"2024-04-18T00:00:00","tipoSorteoCode":"Tres_Monazos","tipoSorteoName":"Tres_Monazos"},"mediaTarde":{"hora":2,"numeros":["3","0","7"],"sorteo_Id":-1,"numeroSorteo":3649,"fecha":"2024-02-16T16:30:00","estado":3,"vigencia":"2024-04-18T00:00:00","tipoSorteoCode":"Tres_Monazos","tipoSorteoName":"Tres_Monazos"},"tarde":{"hora":3,"numeros":["1","9","1"],"sorteo_Id":-1,"numeroSorteo":3650,"fecha":"2024-02-16T19:30:00","estado":3,"vigencia":"2024-04-18T00:00:00","tipoSorteoCode":"Tres_Monazos","tipoSorteoName":"Tres_Monazos"}}