{"dia":"2024-09-03T00:00:00","manana":{"hora":1,"numeros":["6","3","0"],"sorteo_Id":-1,"numeroSorteo":4236,"fecha":"2024-09-03T12:55:00","estado":3,"vigencia":"2024-11-04T00:00:00","tipoSorteoCode":"Tres_Monazos","tipoSorteoName":"Tres_Monazos"},"mediaTarde":{"hora":2,"numeros":["8","5","7"],"sorteo_Id":-1,"numeroSorteo":4237,"fecha":"2024-09-03T16:30:00","estado":3,"vigencia":"2024-11-04T00:00:00","tipoSorteoCode":"Tres_Monazos","tipoSorteoName":"Tres_Monazos"},"tarde":{"hora":3,"numeros":["0","1","2"],"sorteo_Id":-1,"numeroSorteo":4238,"fecha":"2024-09-03T19:30:00","estado":3,"vigencia":"2024-11-04T00:00:00","tipoSorteoCode":"Tres_Monazos","tipoSorteoName":"Tres_Monazos"}}