{"dia":"2024-09-29T00:00:00","manana":{"hora":1,"numeros":["5","3","3"],"sorteo_Id":-1,"numeroSorteo":4314,"fecha":"2024-09-29T12:55:00","estado":3,"vigencia":"2024-11-28T00:00:00","tipoSorteoCode":"Tres_Monazos","tipoSorteoName":"Tres_Monazos"},"mediaTarde":{"hora":2,"numeros":["9","3","2"],"sorteo_Id":-1,"numeroSorteo":4315,"fecha":"2024-09-29T16:30:00","estado":3,"vigencia":"2024-11-28T00:00:00","tipoSorteoCode":"Tres_Monazos","tipoSorteoName":"Tres_Monazos"},"tarde":{"hora":3,"numeros":["2","7","3"],"sorteo_Id":-1,"numeroSorteo":4316,"fecha":"2024-09-29T19:30:00","estado":3,"vigencia":"2024-11-28T00:00:00","tipoSorteoCode":"Tres_Monazos","tipoSorteoName":"Tres_Monazos"}}