{"dia":"2022-07-22T00:00:00","manana":{"hora":1,"numero":79,"meganNumero":-1,"premio":70,"in_reventado":3,"sorteo_Id":-1,"numeroSorteo":19528,"fecha":"2022-07-22T12:55:00","estado":3,"vigencia":"2022-09-22T00:00:00","tipoSorteoCode":"nuevostiempos","tipoSorteoName":"Nuevos Tiempos","porcentaje":90,"colorBolita":"VERDE","descripcionBolita":"Paga 90 veces Modalidad Reventados"},"mediaTarde":{"hora":2,"numero":69,"meganNumero":-1,"premio":70,"in_reventado":0,"sorteo_Id":-1,"numeroSorteo":19529,"fecha":"2022-07-22T16:30:00","estado":3,"vigencia":"2022-09-22T00:00:00","tipoSorteoCode":"nuevostiempos","tipoSorteoName":"Nuevos Tiempos","porcentaje":70,"colorBolita":"BLANCA","descripcionBolita":"Paga 70 veces el Exacto"},"tarde":{"hora":3,"numero":46,"meganNumero":-1,"premio":70,"in_reventado":3,"sorteo_Id":-1,"numeroSorteo":19530,"fecha":"2022-07-22T19:30:00","estado":3,"vigencia":"2022-09-22T00:00:00","tipoSorteoCode":"nuevostiempos","tipoSorteoName":"Nuevos Tiempos","porcentaje":90,"colorBolita":"VERDE","descripcionBolita":"Paga 90 veces Modalidad Reventados"}}