{"dia":"2023-07-09T00:00:00","manana":{"hora":1,"numero":80,"meganNumero":-1,"premio":70,"in_reventado":0,"sorteo_Id":-1,"numeroSorteo":20564,"fecha":"2023-07-09T12:55:00","estado":3,"vigencia":"2023-09-07T00:00:00","tipoSorteoCode":"nuevostiempos","tipoSorteoName":"Nuevos Tiempos","porcentaje":70,"colorBolita":"BLANCA","descripcionBolita":"Paga 70 veces el Exacto"},"mediaTarde":{"hora":2,"numero":21,"meganNumero":-1,"premio":70,"in_reventado":0,"sorteo_Id":-1,"numeroSorteo":20565,"fecha":"2023-07-09T16:30:00","estado":3,"vigencia":"2023-09-07T00:00:00","tipoSorteoCode":"nuevostiempos","tipoSorteoName":"Nuevos Tiempos","porcentaje":70,"colorBolita":"BLANCA","descripcionBolita":"Paga 70 veces el Exacto"},"tarde":{"hora":3,"numero":83,"meganNumero":-1,"premio":70,"in_reventado":0,"sorteo_Id":-1,"numeroSorteo":20566,"fecha":"2023-07-09T19:30:00","estado":3,"vigencia":"2023-09-07T00:00:00","tipoSorteoCode":"nuevostiempos","tipoSorteoName":"Nuevos Tiempos","porcentaje":70,"colorBolita":"BLANCA","descripcionBolita":"Paga 70 veces el Exacto"}}