{"dia":"2024-10-27T00:00:00","manana":{"hora":1,"numero":9,"meganNumero":47,"premio":70,"in_reventado":0,"sorteo_Id":-1,"numeroSorteo":21972,"fecha":"2024-10-27T12:55:00","estado":3,"vigencia":"2024-12-26T00:00:00","tipoSorteoCode":"nuevostiempos","tipoSorteoName":"Nuevos Tiempos","porcentaje":70,"colorBolita":"BLANCA","descripcionBolita":"Paga 70 veces el Exacto"},"mediaTarde":{"hora":2,"numero":73,"meganNumero":20,"premio":70,"in_reventado":1,"sorteo_Id":-1,"numeroSorteo":21973,"fecha":"2024-10-27T16:30:00","estado":3,"vigencia":"2024-12-26T00:00:00","tipoSorteoCode":"nuevostiempos","tipoSorteoName":"Nuevos Tiempos","porcentaje":200,"colorBolita":"ROJA","descripcionBolita":"Paga 200 veces Modalidad Reventados"},"tarde":{"hora":3,"numero":83,"meganNumero":48,"premio":70,"in_reventado":1,"sorteo_Id":-1,"numeroSorteo":21974,"fecha":"2024-10-27T19:30:00","estado":3,"vigencia":"2024-12-26T00:00:00","tipoSorteoCode":"nuevostiempos","tipoSorteoName":"Nuevos Tiempos","porcentaje":200,"colorBolita":"ROJA","descripcionBolita":"Paga 200 veces Modalidad Reventados"}}