{"dia":"2024-12-16T00:00:00","manana":{"hora":1,"numero":70,"meganNumero":29,"premio":70,"in_reventado":0,"sorteo_Id":-1,"numeroSorteo":22122,"fecha":"2024-12-16T12:55:00","estado":3,"vigencia":"2025-02-14T00:00:00","tipoSorteoCode":"nuevostiempos","tipoSorteoName":"Nuevos Tiempos","porcentaje":70,"colorBolita":"BLANCA","descripcionBolita":"Paga 70 veces el Exacto"},"mediaTarde":{"hora":2,"numero":2,"meganNumero":16,"premio":70,"in_reventado":0,"sorteo_Id":-1,"numeroSorteo":22123,"fecha":"2024-12-16T16:30:00","estado":3,"vigencia":"2025-02-14T00:00:00","tipoSorteoCode":"nuevostiempos","tipoSorteoName":"Nuevos Tiempos","porcentaje":70,"colorBolita":"BLANCA","descripcionBolita":"Paga 70 veces el Exacto"},"tarde":{"hora":3,"numero":67,"meganNumero":96,"premio":70,"in_reventado":0,"sorteo_Id":-1,"numeroSorteo":22124,"fecha":"2024-12-16T19:30:00","estado":3,"vigencia":"2025-02-14T00:00:00","tipoSorteoCode":"nuevostiempos","tipoSorteoName":"Nuevos Tiempos","porcentaje":70,"colorBolita":"BLANCA","descripcionBolita":"Paga 70 veces el Exacto"}}